Metadata-Version: 1.0
Name: vin2proxy
Version: 0.0
Summary: vin to vin proxy conversion
Home-page: UNKNOWN
Author: UNKNOWN
Author-email: amankumar.gupta@maruti.co.in
License: UNKNOWN
Platform: UNKNOWN
